{
  "schedules": [
    {
      "name": "pre_briefing_collection",
      "cron": "45 6 * * *",
      "targets": "all",
      "parameters": { "scope": "today" }
    },
    {
      "name": "morning_briefing",
      "cron": "0 7 * * *",
      "targets": ["coordinator"],
      "parameters": { "type": "morning_briefing" }
    },
    {
      "name": "lead_decay_scan",
      "cron": "0 9 * * *",
      "targets": ["relationship"],
      "parameters": { "decayThresholdDays": 14 }
    },
    {
      "name": "compliance_daily",
      "cron": "5 9 * * *",
      "targets": ["compliance"],
      "parameters": { "scope": "disclosure_deadlines_today" }
    },
    {
      "name": "transaction_milestone_check",
      "cron": "10 9 * * *",
      "targets": ["transaction"],
      "parameters": { "scope": "deadlines_within_3_days" }
    },
    {
      "name": "midday_checkin",
      "cron": "0 12 * * *",
      "targets": ["coordinator"],
      "parameters": { "type": "midday_checkin" },
      "enabled": false
    },
    {
      "name": "end_of_day_summary",
      "cron": "30 17 * * *",
      "targets": "all",
      "parameters": { "type": "eod_summary" }
    },
    {
      "name": "knowledge_daily_digest",
      "cron": "0 22 * * *",
      "targets": ["knowledge_base"],
      "parameters": { "type": "daily_digest" }
    },
    {
      "name": "pipeline_summary",
      "cron": "0 8 * * MON",
      "targets": ["relationship", "transaction"],
      "parameters": { "scope": "weekly_pipeline" }
    },
    {
      "name": "sphere_nurture_check",
      "cron": "0 8 * * TUE",
      "targets": ["relationship"],
      "parameters": { "scope": "milestones_this_week" }
    },
    {
      "name": "competitive_scan",
      "cron": "0 8 * * WED",
      "targets": ["research"],
      "parameters": { "scope": "farm_area_changes" }
    },
    {
      "name": "content_batch",
      "cron": "0 8 * * THU",
      "targets": ["content"],
      "parameters": { "scope": "draft_next_week" }
    },
    {
      "name": "market_snapshot",
      "cron": "0 8 * * FRI",
      "targets": ["research"],
      "parameters": { "scope": "weekly_market_metrics" }
    },
    {
      "name": "compliance_weekly",
      "cron": "0 16 * * FRI",
      "targets": ["compliance"],
      "parameters": { "scope": "weekly_flag_summary" }
    },
    {
      "name": "monthly_activity_report",
      "cron": "0 8 1 * *",
      "targets": ["ops"],
      "parameters": { "scope": "monthly_report" }
    },
    {
      "name": "sphere_audit",
      "cron": "0 9 1 * *",
      "targets": ["relationship"],
      "parameters": { "untouchedThresholdDays": 60 }
    },
    {
      "name": "knowledge_refresh",
      "cron": "0 10 1 * *",
      "targets": ["knowledge_base", "research"],
      "parameters": { "scope": "neighborhood_profiles" }
    },
    {
      "name": "past_client_reactivation",
      "cron": "0 9 15 * *",
      "targets": ["relationship"],
      "parameters": { "scope": "home_value_updates" }
    }
  ],
  "timezone": "America/Los_Angeles"
}
